{
  "name" : "EleCon",
  "preName" : "",
  "comment" : null,
  "templateGroupName" : "Default",
  "fullColumn" : [ {
    "name" : "id",
    "comment" : null,
    "type" : null,
    "shortType" : null,
    "custom" : false,
    "ext" : { }
  }, {
    "name" : "rid",
    "comment" : null,
    "type" : null,
    "shortType" : null,
    "custom" : false,
    "ext" : { }
  }, {
    "name" : "eventTime",
    "comment" : null,
    "type" : null,
    "shortType" : null,
    "custom" : false,
    "ext" : { }
  }, {
    "name" : "papRDiff",
    "comment" : null,
    "type" : null,
    "shortType" : null,
    "custom" : false,
    "ext" : { }
  } ],
  "pkColumn" : null,
  "otherColumn" : null,
  "savePackageName" : "com",
  "savePath" : "./src/main/java/com",
  "saveModelName" : "ElectricityConsumption"
}